README.txt
setup.py
src/gocept/__init__.py
src/gocept.ooodocma.egg-info/PKG-INFO
src/gocept.ooodocma.egg-info/SOURCES.txt
src/gocept.ooodocma.egg-info/dependency_links.txt
src/gocept.ooodocma.egg-info/entry_points.txt
src/gocept.ooodocma.egg-info/namespace_packages.txt
src/gocept.ooodocma.egg-info/not-zip-safe
src/gocept.ooodocma.egg-info/requires.txt
src/gocept.ooodocma.egg-info/top_level.txt
src/gocept/ooodocma/__init__.py
