Metadata-Version: 1.0
Name: gocept.ooodocma
Version: 0.9
Summary: zc.buildout recipe for installing an OpenOffice.org/DocmaServer package
Home-page: ftp://ftp.gocept.com/OOoDocmaServer/
Author: Christian Theune
Author-email: ct@gocept.com
License: ZPL 2.1
Keywords: zope3 buildout
Platform: UNKNOWN
Classifier: Framework :: Buildout
